[
  {
    "slug": "samer-hassan",
    "name_ar": "سامر حسن",
    "name_en": "Samer Hassan",
    "title_ar": "مؤسس أكاديمية كُن — مبتكر التفكير الحسّي® — أول عربي MCC",
    "title_en": "Founder of Kun Academy — Creator of Somatic Thinking® — ICF MCC",
    "bio_ar": "سامر حسن هو مبتكر منهجية التفكير الحسّي® وأول عربي يحصل على شهادة الكوتش المعتمد الماستر (MCC) من الاتحاد الدولي للكوتشينج (ICF). تدرّب على يديه أكثر من ٥٠٠ كوتش في ٤ قارات، وأجرى أكثر من ١٠٬٠٠٠ جلسة كوتشينج فردية. يقود أكاديمية كُن من دبي لتخريج كوتشز يحملون منهجية تبدأ من الجسد.",
    "bio_en": "Samer Hassan is the creator of Somatic Thinking® and the first Arab to earn the Master Certified Coach (MCC) credential from the International Coaching Federation (ICF). He has trained 500+ coaches across 4 continents and conducted 10,000+ individual coaching sessions. He leads Kun Academy from Dubai, graduating coaches who carry a methodology that begins with the body.",
    "photo_url": "/images/samer/samer-coaching-portrait.webp",
    "coach_level": "MCC",
    "credentials": "ICF MCC, ICF Young Leader Award 2019",
    "specialties": "التفكير الحسّي,القيادة,التحول المهني,Somatic Thinking,Leadership,Career Transition",
    "coaching_styles": "التفكير الحسّي,Somatic Thinking",
    "languages": "العربية,English,Italiano",
    "is_visible": true,
    "is_bookable": true,
    "display_order": "1",
    "published": true,
    "last_edited_by": "",
    "last_edited_at": "",
    "content_doc_id_ar": "",
    "content_doc_id_en": ""
  }
]